{"diagram_type": "Mindmaps", "data_path": "../data/v1/mindmaps", "id": 13, "user_query": "Can you create a mindmap that covers the basics of portrait photography? I want to understand lighting techniques, composition rules, camera settings, and posing tips for taking better portraits.", "requirements": ["Include lighting setups (natural light, studio lighting, flash techniques)", "Cover composition principles (rule of thirds, framing, background selection)", "Add camera settings guidance (aperture, ISO, focus modes)", "Include posing tips and directing subjects"], "supplementary": {"type": "pdf", "filename": "portrait_photography_basics.pdf"}, "used_complexity": true}